LICENSE.txt
README.md
setup.py
aggdirect_job_report_utility/__init__.py
aggdirect_job_report_utility.egg-info/PKG-INFO
aggdirect_job_report_utility.egg-info/SOURCES.txt
aggdirect_job_report_utility.egg-info/dependency_links.txt
aggdirect_job_report_utility.egg-info/not-zip-safe
aggdirect_job_report_utility.egg-info/requires.txt
aggdirect_job_report_utility.egg-info/top_level.txt